cabot_alert_webhook/__init__.py
cabot_alert_webhook/models.py
cabot_alert_webhook/migrations/0001_initial.py
cabot_alert_webhook/migrations/__init__.py
cabot_alert_webhooks/__init__.py
cabot_alert_webhooks/models.py
cabot_alert_webhooks/migrations/0001_initial.py
cabot_alert_webhooks/migrations/__init__.py
cabot_alert_webhooks-0.1.0.dist-info/LICENSE
cabot_alert_webhooks-0.1.0.dist-info/METADATA
cabot_alert_webhooks-0.1.0.dist-info/WHEEL
cabot_alert_webhooks-0.1.0.dist-info/top_level.txt
cabot_alert_webhooks-0.1.0.dist-info/RECORD
