Metadata-Version: 2.1
Name: cabot-alert-webhooks
Version: 0.1.0
Summary: A Webhook plugin for Cabot
Home-page: https://github.com/arjunreddyc/cabot-alert-webhook
Author: Nagarjuna Reddy C
Author-email: nagarjuna@playment.in
License: UNKNOWN
Download-URL: https://github.com/arjunreddyc/cabot-alert-webhook/tarball/master
Keywords: cabot,webhook,status check
Platform: UNKNOWN
